gima/__init__.py
gima/gima.py
gima/usage.md
gima/db/Database.py
gima/git/GitRepo.py
gima/git/Settings.py
gima/git/__init__.py
gima/utils/Logger.py
gima/utils/args.py
gima/utils/io.py
gima/utils/regex.py
gima-1.0.35.dist-info/METADATA
gima-1.0.35.dist-info/WHEEL
gima-1.0.35.dist-info/entry_points.txt
gima-1.0.35.dist-info/licenses/LICENSE
gima-1.0.35.dist-info/RECORD
