Metadata-Version: 2.4
Name: gima
Version: 1.0.35
Summary: Software which simplifies managing many git repositories through a console
Project-URL: Homepage, https://gitlab.com/ahypki/gima
Project-URL: Issues, https://gitlab.com/ahypki/gima/-/issues/
Author: Arkadiusz Hypki
License-Expression: MIT
License-File: LICENSE
Classifier: Operating System :: OS Independent
Classifier: Programming Language :: Python :: 3
Requires-Python: >=3.9
